argparse_complete_fig/__init__.py
argparse_complete_fig/fig.py
argparse_complete_fig-1.0.1.dist-info/LICENSE
argparse_complete_fig-1.0.1.dist-info/METADATA
argparse_complete_fig-1.0.1.dist-info/WHEEL
argparse_complete_fig-1.0.1.dist-info/top_level.txt
argparse_complete_fig-1.0.1.dist-info/RECORD
